{
    "chain_names": [
        {
            "number": 1,
            "name": "Chain 0"
        },
        {
            "number": 2,
            "name": "Chain 1"
        }
    ],
    "host": {
        "hostname": "ubntCSE Station",
        "uptime": 18165,
        "time": "2020-06-23 14:43:39",
        "timestamp": 3810719703,
        "fwversion": "v8.7.1",
        "devmodel": "NanoBeam 5AC Gen2",
        "netrole": "bridge",
        "loadavg": 0.456543,
        "totalram": 63447040,
        "freeram": 25587712,
        "temperature": 0,
        "cpuload": 62.376236,
        "height": null
    },
    "genuine": "/images/genuine.png",
    "services": {
        "dhcpc": false,
        "dhcpd": false,
        "dhcp6d_stateful": false,
        "pppoe": false,
        "airview": 2
    },
    "firewall": {
        "iptables": false,
        "ebtables": false,
        "ip6tables": false,
        "eb6tables": false
    },
    "portfw": false,
    "wireless": {
        "essid": "ubntCSE",
        "mode": "sta-ptp",
        "ieeemode": "AUTO",
        "band": 2,
        "compat_11n": 0,
        "hide_essid": 0,
        "apmac": "F4:E2:C6:34:3B:B1",
        "antenna_gain": 19,
        "frequency": 5785,
        "center1_freq": 5795,
        "dfs": 0,
        "distance": 0,
        "security": "WPA2",
        "noisef": -94,
        "txpower": 3,
        "aprepeater": false,
        "rstatus": 5,
        "chanbw": 40,
        "rx_chainmask": 3,
        "tx_chainmask": 3,
        "cac_state": 0,
        "cac_timeout": 0,
        "rx_idx": 8,
        "rx_nss": 2,
        "tx_idx": 9,
        "tx_nss": 2,
        "throughput": {
            "tx": 0,
            "rx": 104358
        },
        "count": 1,
        "polling": {
            "dcap": 298800,
            "ucap": 298800,
            "use": 295,
            "tx_use": 2,
            "rx_use": 293,
            "atpc_status": 0,
            "fixed_frame": false,
            "gps_sync": false,
            "ff_cap_rep": false
        },
        "sta": [
            {
                "mac": "F4:E2:C6:34:3B:B1",
                "lastip": "10.1.1.1",
                "signal": -38,
                "rssi": 58,
                "noisefloor": -94,
                "chainrssi": [
                    50,
                    57,
                    0
                ],
                "tx_idx": 9,
                "rx_idx": 8,
                "tx_nss": 2,
                "rx_nss": 2,
                "tx_latency": 0,
                "distance": 0,
                "tx_packets": 0,
                "tx_lretries": 0,
                "tx_sretries": 0,
                "uptime": 18101,
                "dl_signal_expect": 0,
                "ul_signal_expect": 0,
                "dl_linkscore": 0,
                "ul_linkscore": 0,
                "tx_ratedata": [
                    2,
                    4,
                    5,
                    8,
                    33,
                    424,
                    1424,
                    11604,
                    148795,
                    2652867
                ],
                "stats": {
                    "rx_bytes": 12573661058,
                    "rx_packets": 9845001,
                    "rx_pps": 8545,
                    "tx_bytes": 13908773587,
                    "tx_packets": 10961748,
                    "tx_pps": 0
                },
                "airmax": {
                    "actual_priority": 0,
                    "beam": 0,
                    "desired_priority": 0,
                    "downlink_capacity": 298800,
                    "uplink_capacity": 298800,
                    "atpc_status": 0,
                    "rx": {
                        "usage": 293,
                        "cinr": 26,
                        "evm": [
                            [
                                22,
                                24,
                                25,
                                26,
                                29,
                                25,
                                27,
                                28,
                                25,
                                30,
                                27,
                                25,
                                25,
                                26,
                                27,
                                24,
                                26,
                                25,
                                26,
                                25,
                                26,
                                26,
                                25,
                                25,
                                26,
                                25,
                                27,
                                26,
                                23,
                                26,
                                25,
                                27,
                                25,
                                27,
                                26,
                                25,
                                27,
                                26,
                                25,
                                25,
                                26,
                                28,
                                28,
                                28,
                                24,
                                27,
                                25,
                                25,
                                28,
                                26,
                                24,
                                27,
                                27,
                                25,
                                26,
                                26,
                                26,
                                27,
                                25,
                                28,
                                24,
                                27,
                                28,
                                25
                            ],
                            [
                                54,
                                55,
                                54,
                                56,
                                54,
                                54,
                                54,
                                55,
                                54,
                                55,
                                55,
                                55,
                                54,
                                54,
                                56,
                                55,
                                53,
                                54,
                                55,
                                54,
                                55,
                                54,
                                55,
                                54,
                                54,
                                54,
                                54,
                                55,
                                54,
                                55,
                                54,
                                54,
                                54,
                                53,
                                55,
                                54,
                                54,
                                55,
                                55,
                                55,
                                56,
                                55,
                                53,
                                55,
                                55,
                                56,
                                55,
                                54,
                                54,
                                54,
                                56,
                                55,
                                56,
                                55,
                                55,
                                53,
                                55,
                                54,
                                53,
                                55,
                                56,
                                56,
                                53,
                                52
                            ]
                        ]
                    },
                    "tx": {
                        "usage": 2,
                        "cinr": 27,
                        "evm": [
                            [
                                30,
                                25,
                                29,
                                25,
                                27,
                                29,
                                28,
                                31,
                                26,
                                27,
                                27,
                                30,
                                27,
                                29,
                                29,
                                34,
                                29,
                                30,
                                25,
                                28,
                                28,
                                28,
                                27,
                                28,
                                29,
                                28,
                                26,
                                28,
                                31,
                                26,
                                26,
                                27,
                                26,
                                28,
                                29,
                                26,
                                28,
                                26,
                                25,
                                27,
                                26,
                                27,
                                26,
                                30,
                                25,
                                31,
                                25,
                                25,
                                27,
                                30,
                                27,
                                26,
                                29,
                                28,
                                28,
                                29,
                                29,
                                27,
                                27,
                                27,
                                27,
                                28,
                                24,
                                26
                            ],
                            [
                                58,
                                58,
                                59,
                                59,
                                59,
                                58,
                                59,
                                58,
                                59,
                                60,
                                59,
                                59,
                                59,
                                60,
                                59,
                                60,
                                59,
                                60,
                                60,
                                59,
                                58,
                                59,
                                58,
                                59,
                                59,
                                59,
                                58,
                                58,
                                59,
                                59,
                                58,
                                59,
                                59,
                                59,
                                59,
                                59,
                                58,
                                60,
                                58,
                                58,
                                60,
                                58,
                                59,
                                59,
                                59,
                                59,
                                59,
                                57,
                                58,
                                59,
                                58,
                                59,
                                59,
                                59,
                                59,
                                59,
                                58,
                                59,
                                59,
                                58,
                                58,
                                59,
                                58,
                                58
                            ]
                        ]
                    }
                },
                "remote": {
                    "hostname": "ubntCSE Source",
                    "platform": "NanoBeam 5AC Gen2",
                    "version": "WA.ar934x.v8.7.1.42832.200623.1641",
                    "time": "2020-06-23 14:45:07",
                    "cpuload": 27.0,
                    "temperature": 0,
                    "totalram": 63447040,
                    "freeram": 23699456,
                    "netrole": "bridge",
                    "mode": "ap-ptp",
                    "sys_id": "0xe7fc",
                    "tx_throughput": 104696,
                    "rx_throughput": 0,
                    "uptime": 18253,
                    "compat_11n": 0,
                    "signal": -34,
                    "rssi": 62,
                    "noisefloor": -95,
                    "tx_power": -4,
                    "distance": 0,
                    "rx_chainmask": 3,
                    "chainrssi": [
                        57,
                        60,
                        0
                    ],
                    "tx_ratedata": [
                        3,
                        4,
                        4,
                        8,
                        32,
                        281,
                        1684,
                        7000,
                        134210,
                        1622420
                    ],
                    "tx_bytes": 12842504311,
                    "rx_bytes": 13600294231,
                    "antenna_gain": 19,
                    "height": null,
                    "ethlist": [
                        {
                            "ifname": "eth0",
                            "enabled": true,
                            "plugged": true,
                            "duplex": true,
                            "speed": 1000,
                            "snr": [
                                30,
                                30,
                                30,
                                30
                            ],
                            "cable_len": 1
                        },
                        {
                            "ifname": "eth1",
                            "enabled": true,
                            "plugged": false,
                            "duplex": true,
                            "speed": 0,
                            "snr": [
                                0,
                                0,
                                0,
                                0
                            ],
                            "cable_len": 0
                        }
                    ],
                    "ipaddr": [
                        "10.1.1.1"
                    ],
                    "ip6addr": [
                        "fe80::f6e2:c6ff:fe34:3bb1"
                    ],
                    "oob": false,
                    "unms": {
                        "status": 0
                    },
                    "airview": 2
                }
            }
        ]
    },
    "interfaces": [
        {
            "ifname": "eth0",
            "hwaddr": "F4:E2:C6:35:4E:61",
            "enabled": true,
            "mtu": 1500,
            "status": {
                "plugged": true,
                "tx_bytes": 12860569300,
                "rx_bytes": 13451486271,
                "tx_errors": 0,
                "rx_errors": 0,
                "ipaddr": "0.0.0.0",
                "speed": 100,
                "duplex": true,
                "snr": [
                    30,
                    30,
                    30,
                    30
                ],
                "cable_len": 0
            }
        },
        {
            "ifname": "eth1",
            "hwaddr": "F6:E2:C6:35:4E:61",
            "enabled": true,
            "mtu": 1500,
            "status": {
                "plugged": false,
                "tx_bytes": 0,
                "rx_bytes": 0,
                "tx_errors": 0,
                "rx_errors": 0,
                "ipaddr": "0.0.0.0",
                "speed": 0,
                "duplex": true,
                "snr": [
                    0,
                    0,
                    0,
                    0
                ],
                "cable_len": 0
            }
        },
        {
            "ifname": "ath0",
            "hwaddr": "F4:E2:C6:34:4E:61",
            "enabled": true,
            "mtu": 1500,
            "status": {
                "plugged": false,
                "tx_bytes": 13908773584,
                "rx_bytes": 12573661056,
                "tx_errors": 0,
                "rx_errors": 0,
                "ipaddr": "0.0.0.0",
                "speed": 0,
                "duplex": false
            }
        },
        {
            "ifname": "br0",
            "hwaddr": "F4:E2:C6:34:4E:61",
            "enabled": true,
            "mtu": 1500,
            "status": {
                "plugged": true,
                "tx_bytes": 273342170,
                "rx_bytes": 11471771,
                "tx_errors": 0,
                "rx_errors": 0,
                "ipaddr": "10.1.1.2",
                "ip6addr": [
                    {
                        "addr": "fe80::f6e2:c6ff:fe34:4e61",
                        "plen": 64
                    }
                ],
                "speed": 0,
                "duplex": false
            }
        }
    ],
    "provmode": {},
    "ntpclient": {},
    "unms": {
        "status": 0
    }
}