{
    "tcp": {
        "send": "[  5]   0.00-10.01  sec   114 MBytes  95.6 Mbits/sec                  sender",
        "recv": "[  5]   0.00-10.15  sec   114 MBytes  93.9 Mbits/sec                  receiver"
    },
    "udp": {
        "send": "[  5]   0.00-10.01  sec   113 MBytes  94.6 Mbits/sec  0.000 ms  0/81032 (0%)  sender",
        "recv": "[  5]   0.00-10.02  sec   113 MBytes  94.5 Mbits/sec  0.127 ms  0/81031 (0%)  receiver"
    },
    "reverse_tcp": {
        "send": "[  5]   0.00-10.04  sec   106 MBytes  88.8 Mbits/sec                  sender",
        "recv": "[  5]   0.00-10.01  sec   106 MBytes  88.6 Mbits/sec                  receiver"
    },
    "reverse_udp": {
        "send": "[  5]   0.00-10.01  sec   119 MBytes   100 Mbits/sec  0.000 ms  0/85671 (0%)  sender",
        "recv": "[  5]   0.00-10.01  sec  78.9 MBytes  66.1 Mbits/sec  0.562 ms  28902/85541 (34%)  receiver"
    }
}