{
    "tcp": {
        "send": "[  5]   0.00-10.01  sec   115 MBytes  96.1 Mbits/sec                  sender",
        "recv": "[  5]   0.00-10.13  sec   114 MBytes  94.4 Mbits/sec                  receiver"
    },
    "udp": {
        "send": "[  5]   0.00-10.01  sec   113 MBytes  95.0 Mbits/sec  0.000 ms  0/81419 (0%)  sender",
        "recv": "[  5]   0.00-10.02  sec   105 MBytes  87.7 Mbits/sec  0.111 ms  6187/81419 (7.6%)  receiver"
    },
    "reverse_tcp": {
        "send": "[  5]   0.00-10.00  sec   106 MBytes  88.7 Mbits/sec                  sender",
        "recv": "[  5]   0.00-10.00  sec   106 MBytes  88.5 Mbits/sec                  receiver"
    },
    "reverse_udp": {
        "send": "[  5]   0.00-10.02  sec   119 MBytes  99.9 Mbits/sec  0.000 ms  0/85688 (0%)  sender",
        "recv": "[  5]   0.00-10.01  sec  64.2 MBytes  53.8 Mbits/sec  0.070 ms  39493/85636 (46%)  receiver"
    }
}